hestcore/__init__.py
hestcore/datasets.py
hestcore/segmentation.py
hestcore/singletons.py
hestcore/vst_save_utils.py
hestcore/wsi.py
hestcore-1.0.6.dist-info/LICENSE.md
hestcore-1.0.6.dist-info/METADATA
hestcore-1.0.6.dist-info/WHEEL
hestcore-1.0.6.dist-info/top_level.txt
hestcore-1.0.6.dist-info/RECORD
