Metadata-Version: 2.2
Name: hestcore
Version: 1.0.6
Author-email: Paul Doucet <pdoucet@bwh.harvard.edu>, Guillaume Jaume <gjaume@bwh.harvard.edu>
Requires-Python: >=3.9
License-File: LICENSE.md
Requires-Dist: scanpy>=1.10.1
Requires-Dist: imagecodecs>=2024.1.1
Requires-Dist: pytorch-lightning>=2.2.4
Requires-Dist: openslide-python>=1.3.1
Requires-Dist: pyarrow>=16.1.0
Requires-Dist: datasets
Requires-Dist: geopandas
